protobuf_odigos-4.23.4-py3.9-nspkg.pth
google_odigos/protobuf/__init__.py
google_odigos/protobuf/descriptor.py
google_odigos/protobuf/descriptor_database.py
google_odigos/protobuf/descriptor_pool.py
google_odigos/protobuf/json_format.py
google_odigos/protobuf/message.py
google_odigos/protobuf/message_factory.py
google_odigos/protobuf/proto_builder.py
google_odigos/protobuf/reflection.py
google_odigos/protobuf/service.py
google_odigos/protobuf/service_reflection.py
google_odigos/protobuf/symbol_database.py
google_odigos/protobuf/text_encoding.py
google_odigos/protobuf/text_format.py
google_odigos/protobuf/unknown_fields.py
google_odigos/protobuf/compiler/__init__.py
google_odigos/protobuf/internal/__init__.py
google_odigos/protobuf/internal/api_implementation.py
google_odigos/protobuf/internal/builder.py
google_odigos/protobuf/internal/containers.py
google_odigos/protobuf/internal/decoder.py
google_odigos/protobuf/internal/encoder.py
google_odigos/protobuf/internal/enum_type_wrapper.py
google_odigos/protobuf/internal/extension_dict.py
google_odigos/protobuf/internal/field_mask.py
google_odigos/protobuf/internal/message_listener.py
google_odigos/protobuf/internal/python_message.py
google_odigos/protobuf/internal/type_checkers.py
google_odigos/protobuf/internal/well_known_types.py
google_odigos/protobuf/internal/wire_format.py
google_odigos/protobuf/internal/numpy/__init__.py
google_odigos/protobuf/pyext/__init__.py
google_odigos/protobuf/pyext/cpp_message.py
google_odigos/protobuf/util/__init__.py
protobuf_odigos-4.23.4.dist-info/METADATA
protobuf_odigos-4.23.4.dist-info/WHEEL
protobuf_odigos-4.23.4.dist-info/namespace_packages.txt
protobuf_odigos-4.23.4.dist-info/top_level.txt
protobuf_odigos-4.23.4.dist-info/RECORD
